MANIFEST.in
setup.py
redsolution_setup/__init__.py
redsolution_setup/make.py
redsolution_setup/templates/settings.pyt
redsolution_setup/templates/urls.pyt
redsolutioncms.django_photologue.egg-info/PKG-INFO
redsolutioncms.django_photologue.egg-info/SOURCES.txt
redsolutioncms.django_photologue.egg-info/dependency_links.txt
redsolutioncms.django_photologue.egg-info/entry_points.txt
redsolutioncms.django_photologue.egg-info/not-zip-safe
redsolutioncms.django_photologue.egg-info/requires.txt
redsolutioncms.django_photologue.egg-info/top_level.txt