Metadata-Version: 1.0
Name: redsolutioncms.django-photologue
Version: 0.1.0
Summary: It's an application, that provides your an photologue.
Home-page: UNKNOWN
Author: Julia Tolipova
Author-email: julia.tolipova@redsolution.ru
License: GPLv3
Keywords: django photologue
Platform: UNKNOWN
Classifier: Development Status :: 3 - Alpha
Classifier: Intended Audience :: Developers
Classifier: License :: OSI Approved :: GNU General Public License (GPL)
Classifier: Framework :: Django
Classifier: Environment :: Web Environment
Classifier: Natural Language :: Russian
Classifier: Natural Language :: English
Classifier: Operating System :: OS Independent
Classifier: Programming Language :: Python
Classifier: Topic :: Internet :: WWW/HTTP :: Dynamic Content
